Metadata-Version: 1.0
Name: kafka-api
Version: 0.1.1
Summary: High level API for Apache Kafka (over kafka-python lib)
Home-page: UNKNOWN
Author: Evgeniy Polyak
Author-email: epolyak@yandex.ru
License: UNKNOWN
Platform: UNKNOWN
